CHANGELOG.md
skmpe/__init__.py
skmpe/_api.py
skmpe/_base.py
skmpe/_exceptions.py
skmpe/_mpe.py
skmpe/_parameters.py
scikit_mpe-0.2.4.dist-info/LICENSE
scikit_mpe-0.2.4.dist-info/WHEEL
scikit_mpe-0.2.4.dist-info/METADATA
scikit_mpe-0.2.4.dist-info/RECORD
