Metadata-Version: 2.1
Name: scikit-mpe
Version: 0.2.4
Summary: Minimal path extraction using the fast marching method
Home-page: https://github.com/espdev/scikit-mpe
License: MIT
Keywords: mpe,fmm,minimal-path,fast-marching,fast-marching-method,scikit
Author: Eugene Prilepin
Author-email: esp.home@gmail.com
Requires-Python: >=3.6,<4.0
Classifier: Development Status :: 4 - Beta
Classifier: Intended Audience :: Developers
Classifier: Intended Audience :: Science/Research
Classifier: License :: OSI Approved :: MIT License
Classifier: Programming Language :: Python
Classifier: Programming Language :: Python :: 3
Classifier: Programming Language :: Python :: 3 :: Only
Classifier: Programming Language :: Python :: 3.6
Classifier: Programming Language :: Python :: 3.7
Classifier: Programming Language :: Python :: 3.8
Classifier: Programming Language :: Python :: 3.9
Classifier: Programming Language :: Python :: Implementation :: CPython
Classifier: Topic :: Scientific/Engineering
Classifier: Topic :: Scientific/Engineering :: Mathematics
Classifier: Topic :: Software Development :: Libraries
Provides-Extra: docs
Requires-Dist: importlib-metadata (>=1.6.0,<2.0.0)
Requires-Dist: m2r (>=0.2.1,<0.3.0); extra == "docs"
Requires-Dist: matplotlib (>=3.1.3,<4.0.0); extra == "docs"
Requires-Dist: numpy (>=1.18.1,<2.0.0)
Requires-Dist: numpydoc (>=0.9.2,<0.10.0); extra == "docs"
Requires-Dist: pydantic (>=1.4,<2.0)
Requires-Dist: scikit-fmm (>=2021.1.21,<2022.0.0)
Requires-Dist: scikit-image (>=0.16.2,<0.17.0); extra == "docs"
Requires-Dist: scipy (>=1.4.1,<2.0.0)
Requires-Dist: sphinx (>=2.3.1,<3.0.0); extra == "docs"
Project-URL: Documentation, https://scikit-mpe.readthedocs.io/en/latest
Project-URL: Repository, https://github.com/espdev/scikit-mpe
